<PAMDataset>
  <Metadata>
    <MDI key="DataType">Generic</MDI>
  </Metadata>
  <Metadata domain="Esri">
    <MDI key="PyramidResamplingType">NEAREST</MDI>
  </Metadata>
  <PAMRasterBand band="1">
    <Histograms>
      <HistItem>
        <HistMin>5.032376766204834</HistMin>
        <HistMax>7.271407127380371</HistMax>
        <BucketCount>256</BucketCount>
        <IncludeOutOfRange>1</IncludeOutOfRange>
        <Approximate>0</Approximate>
        <HistCounts>39|92|146|207|274|312|405|466|586|621|677|720|732|800|786|833|893|888|942|994|1054|1090|1238|1540|1583|1655|1758|1755|1748|1744|1750|1743|1721|1723|1710|1696|1695|1693|1691|1699|1694|1686|1692|1708|1720|1745|1749|1749|1705|1719|1722|1726|1816|1883|1911|1924|1880|1912|1913|1891|1899|1932|1930|1951|1982|1958|2036|2032|2096|2104|2069|2085|2020|2046|2004|2028|1987|2006|1976|2000|1928|1929|1847|1861|1835|1828|1829|1806|1864|1823|1833|1828|1809|1812|1790|1767|1792|1746|1738|1756|1720|1714|1731|1700|1694|1686|1686|1666|1669|1672|1665|1647|1630|1651|1649|1617|1614|1617|1619|1610|1603|1605|1605|1626|1615|1593|1594|1595|1591|1605|1613|1587|1593|1582|1589|1569|1573|1568|1560|1551|1541|1539|1527|1523|1522|1512|1510|1496|1499|1469|1489|1467|1459|1460|1451|1434|1425|1399|1387|1335|1309|1294|1274|1255|1243|1223|1210|1195|1181|1161|1136|1123|1120|1100|1093|1079|1075|1064|1051|1051|1038|1030|1027|1016|1009|999|991|963|959|949|942|935|914|905|896|878|864|832|835|813|800|795|787|762|748|716|722|710|686|669|655|635|610|578|555|547|533|511|485|459|436|408|348|341|318|287|276|259|250|239|224|211|199|190|184|174|170|160|157|145|145|139|134|132|128|123|110|98|87|73|66|49|40|23|10|1</HistCounts>
      </HistItem>
    </Histograms>
    <Metadata>
      <MDI key="RepresentationType">ATHEMATIC</MDI>
      <MDI key="STATISTICS_COVARIANCES">0.2482253561302543</MDI>
      <MDI key="STATISTICS_MAXIMUM">7.2714071273804</MDI>
      <MDI key="STATISTICS_MEAN">5.9586002944236</MDI>
      <MDI key="STATISTICS_MINIMUM">5.0323767662048</MDI>
      <MDI key="STATISTICS_SKIPFACTORX">1</MDI>
      <MDI key="STATISTICS_SKIPFACTORY">1</MDI>
      <MDI key="STATISTICS_STDDEV">0.49822219554156</MDI>
    </Metadata>
  </PAMRasterBand>
</PAMDataset>
